pubmed_lookup-0.2.3.dist-info/RECORD
pubmed_lookup-0.2.3.dist-info/metadata.json
pubmed_lookup-0.2.3.dist-info/WHEEL
pubmed_lookup-0.2.3.dist-info/entry_points.txt
pubmed_lookup-0.2.3.dist-info/DESCRIPTION.rst
pubmed_lookup-0.2.3.dist-info/top_level.txt
pubmed_lookup-0.2.3.dist-info/METADATA
pubmed_lookup/test_pubmed_lookup.py
pubmed_lookup/command_line.py
pubmed_lookup/__init__.py
pubmed_lookup/pubmed_lookup.py
