Metadata-Version: 1.1
Name: pubmed-lookup
Version: 0.2.3
Summary: Lookup PubMed records and make Publication objects with info about a scientific publication
Home-page: https://github.com/mfcovington/pubmed-lookup
Author: Michael F. Covington
Author-email: mfcovington@gmail.com
License: BSD License
Keywords: citations lab literature pmid publications pubmed science
Platform: UNKNOWN
Classifier: Development Status :: 3 - Alpha
Classifier: Intended Audience :: Developers
Classifier: Intended Audience :: Science/Research
Classifier: License :: OSI Approved :: BSD License
Classifier: Operating System :: OS Independent
Classifier: Programming Language :: Python
Classifier: Programming Language :: Python :: 3
Classifier: Programming Language :: Python :: 3.3
Classifier: Programming Language :: Python :: 3.4
Classifier: Programming Language :: Python :: 3.5
Classifier: Programming Language :: Python :: 3.6
Classifier: Programming Language :: Python :: 3.7
Classifier: Programming Language :: Python :: 3 :: Only
